setup.py
Gentlemen.egg-info/PKG-INFO
Gentlemen.egg-info/SOURCES.txt
Gentlemen.egg-info/dependency_links.txt
Gentlemen.egg-info/entry_points.txt
Gentlemen.egg-info/top_level.txt
gentlemen/__init__.py