Metadata-Version: 1.0
Name: Gentlemen
Version: 0.0.1
Summary: This is gentlemen
Home-page: UNKNOWN
Author: Gerald Kaszuba
Author-email: gak@gak0.com
License: UNKNOWN
Platform: UNKNOWN
